Workbook

Sheet Sheet1
B2: CA Name
B3: B.Com., ACA., LCS., (CIMA – UK)
B4: Chartered Accountant
B5: Address
B6: Address
E8: Cert. No.:
E9: 43049
B11: NET WORTH CERTIFICATE
B13: We hereby certify below the position of Assets & Liabilities of the persons mentioned hereunder as on 10.11.2017
B14: The same has been verified from the records & other details produced before us:
B15: Name | C15: PAN | D15: Date of Birth | E15: Permanent Address
B21: (A) Total Value of Immovable Property:
B22: (This includes beneficial share owned in Land, Building, Flat, Factory, Shop, House etc.)
B24: Nature of Property | C24: Location with Complete Address | D24: Value at Cost ( ` In Lacs)
B25: Plot at
B26: TOTAL | D26: =SUM(D25:D25) -> 0
B29: (B) Total Value of Other Assets: (As per Annexure -1 Attached)
B30: (This includes Cash, Bank balance, Gold, Other Jewellery,
B31: Investment in Shares/Mutual Funds/FD’s/LIC etc, Vehicles, Capital in Business etc.)
B33: Nature of Asset | C33: Particulars of Asset/ Complete Description | D33: Oty. | E33: Value at Cost ( ` In Lacs)
B34: EPF | C34: EPF | D34: 1 | E34: =(SUM(Sheet2!D8))/100000 -> 0
B35: LIC Policy | C35: Insurance | D35: 6 | E35: =Sheet2!D17/100000 -> 0
B36: Jewellery | E36: =SUM(Sheet2!D16)/100000 -> 0
B37: Cash in hand | D37: 1 | E37: =(SUM(Sheet2!D7))/100000 -> 0
B38: FDR & Bank | C38: FDR & Bank | D38: 5 | E38: =(SUM(Sheet2!D9:D15))/100000 -> 0
B39: TOTAL | E39: =SUM(E34:E38) -> 0
B42: (C) Total Liabilities:
B44: Borrowed From | C44: Amount & Securities offered | D44: Purpose | E44: O/s as on date ( ` In Lacs)
B45: - | C45: - | D45: - | E45: 0
B46: TOTAL | E46: =SUM(E45:E45) -> 0
B49: (D) Net Worth: (A + B – C) = ` in Lacs | E49: =+D26+E39-E46 -> 0
B50: (In words Sixty Five Lakhs Ninety Thousand Only)
B52: (E) Networth: in $ | E52: =+E49/68*100000 -> 0
B53: He/She is the Guarantor for various Borrowings by his/her friends / relatives / firm(s) / company(s) as detailed hereby | E53: NIL
B56: As per records produced before me
B60: CA Name
B61: Chartered Accountant
B62: Membership Number: XXXXXX
B63: Date: 10/11/2016

Sheet Sheet2
B3: Annexure 1 - Details of Other Assets
B6: Particulars | C6: A/c No. | D6: Amount | E6: Amount (` in Lacs) | F6: Belongs to | G6: Relationship
B7: Cash | E7: =+D7/100000 -> 0 | F7: =Sheet1!B16 -> 0 | G7: Self
B8: EPF | E8: =+D8/100000 -> 0 | F8: =Sheet1!B16 -> 0 | G8: Self
B9: SBI FDR | E9: =+D9/100000 -> 0 | F9: =Sheet1!B17 -> 0 | G9: Father
B10: SBI FDR | E10: =+D10/100000 -> 0 | F10: =Sheet1!B17 -> 0 | G10: Father
B11: SBI FDR | E11: =+D11/100000 -> 0 | F11: =Sheet1!B17 -> 0 | G11: Father
B12: Canara Bank FDR | E12: =+D12/100000 -> 0 | F12: =Sheet1!B17 -> 0 | G12: Father
B13: Indian Bank FDR | E13: =+D13/100000 -> 0 | F13: =Sheet1!B18 -> 0 | G13: Mother
B14: Saidapet Co-operative FDR | E14: =+D14/100000 -> 0 | F14: =Sheet1!B18 -> 0 | G14: Mother
B15: SBI FDR | E15: =+D15/100000 -> 0 | G15: Elder Brother
B16: Jewellery | E16: =+D16/100000 -> 0 | F16: =Sheet1!B18 -> 0 | G16: Mother
B17: LIC Policy | E17: =+D17/100000 -> 0 | F17: =Sheet1!B16 -> 0 | G17: Self
D24: =SUM(D7:D21) -> 0 | E24: =SUM(E7:E23) -> 0
